{
  "seo": {
    "title": "内容创作去中心化应用（dApp）",
    "description": "YOUR协议是一个开源协议，允许开发人员参与代码开发并获得其贡献的奖励。",
    "keywords": ""
  },
  "hero": {
    "title": "内容创作去中心化应用（dApp）",
    "paragraphs": [
      "在YOUR协议上构建您自己的产品内容创作去中心化应用（dApp）。",
      "将您的产品内容接入Web2/Web3电子商务世界的门户。以高效、可控和去中心化的方式登记、存储和分发您的产品内容。"
    ],
    "cta": "加入去中心化应用（dApp）"
  },
  "intro": {
    "title": "完全掌控您的产品内容并获得收益"
  },
  "block1": {
    "title": "构建内容创作的未来",
    "paragraphs": [
      "YOUR的开源协议使去中心化应用（dApp）能够在高效、去中心化、创新和安全的网络上构建自己的应用程序。",
      "YOUR将产品内容创作带入了一个新时代，每个人都可以构建、贡献和获得收益。"
    ],
    "alt": "YOUR 去中心化应用（dApp）内容创作协议"
  },
  "block2": {
    "title": "质押并构建",
    "paragraphs": [
      "为了使用YOUR协议的内容创作去中心化应用（dApp），首先需要质押一定数量的代币。",
      "质押后，去中心化应用（dApp）将能够根据其对控制、分发和奖励的需求来配置其应用程序到协议的端点和服务。"
    ],
    "alt": "YOUR 去中心化应用（dApp）开发未来",
    "cta": "加入去中心化应用（dApp）"
  }
}
